tenuml-1.1.1.4.data/purelib/tenuml/__init__.py
tenuml-1.1.1.4.data/purelib/tenuml/_libnuml.so
tenuml-1.1.1.4.data/purelib/tenuml/libnuml.py
tenuml-1.1.1.4.dist-info/METADATA
tenuml-1.1.1.4.dist-info/WHEEL
tenuml-1.1.1.4.dist-info/top_level.txt
tenuml-1.1.1.4.dist-info/RECORD
