Metadata-Version: 2.1
Name: tenuml
Version: 1.1.1.4
Summary: Library for reading/writing data in COMBINE archives
Home-page: https://github.com/NuML/NuML
Author: Frank Bergmann, Kyle Medley (packaging)
Author-email: UNKNOWN
License: UNKNOWN
Platform: UNKNOWN
Classifier: Intended Audience :: Science/Research
Classifier: Operating System :: MacOS :: MacOS X
Classifier: Operating System :: Microsoft :: Windows
Classifier: Operating System :: POSIX
Classifier: Programming Language :: C++
